LICENSE.txt
MANIFEST
Untitled.ipynb
reload.sh
setup.cfg
setup.py
upload.sh
.idea/.gitignore
.idea/ceneo.iml
.idea/misc.xml
.idea/modules.xml
.idea/vcs.xml
.idea/inspectionProfiles/profiles_settings.xml
.ipynb_checkpoints/Untitled-checkpoint.ipynb
__pycache__/test.cpython-37.pyc
ceneo/README.md
ceneo/__init__.py
ceneo/lib.py
ceneo.egg-info/PKG-INFO
ceneo.egg-info/SOURCES.txt
ceneo.egg-info/dependency_links.txt
ceneo.egg-info/requires.txt
ceneo.egg-info/top_level.txt
ceneo/__pycache__/__init__.cpython-37.pyc
ceneo/__pycache__/google.cpython-37.pyc
ceneo/__pycache__/lib.cpython-37.pyc
ceneo/__pycache__/predict.cpython-37.pyc
ceneo/__pycache__/tf_idf.cpython-37.pyc
qwant.egg-info/PKG-INFO
qwant.egg-info/SOURCES.txt
qwant.egg-info/dependency_links.txt
qwant.egg-info/requires.txt
qwant.egg-info/top_level.txt